<databaseChangeLog xmlns="http://www.liquibase.org/xml/ns/dbchangelog"
                   xmlns:xsi="http://www.w3.org/2001/XMLSchema-instance"
                   xsi:schemaLocation="http://www.liquibase.org/xml/ns/dbchangelog http://www.liquibase.org/xml/ns/dbchangelog/dbchangelog-4.10.xsd">
    <changeSet id="insert-data-indications" author="kostik">
<!--        <insert tableName="indications"-->
<!--                schemaName="monitoring">-->
<!--            <column name="user_id" value="1"/>-->
<!--            <column name="counter_id" value="1"/>-->
<!--            <column name="value" value="100"/>-->
<!--        </insert>-->
<!--        <insert tableName="indications"-->
<!--                schemaName="monitoring">-->
<!--            <column name="user_id" value="1"/>-->
<!--            <column name="counter_id" value="2"/>-->
<!--            <column name="value" value="100"/>-->
<!--        </insert>-->
<!--        <insert tableName="indications"-->
<!--                schemaName="monitoring">-->
<!--            <column name="user_id" value="1"/>-->
<!--            <column name="counter_id" value="3"/>-->
<!--            <column name="value" value="100"/>-->
<!--        </insert>-->
    </changeSet>
</databaseChangeLog>